Metadata-Version: 1.1
Name: ansilog
Version: 1.6
Summary: Smart and colorful solution for logging, output, and basic terminal control.
Home-page: https://github.com/lainproliant/ansilog
Author: Lain Supe (lainproliant)
Author-email: lainproliant@gmail.com
License: BSD
Keywords: ANSI CLI terminal color colour
Platform: UNKNOWN
Classifier: Development Status :: 4 - Beta
Classifier: Intended Audience :: Developers
Classifier: Topic :: Software Development :: Libraries :: Application Frameworks
Classifier: License :: OSI Approved :: BSD License
Classifier: Programming Language :: Python :: 3
Classifier: Programming Language :: Python :: 3.8
